langgraph/checkpoint/mysql/__init__.py
langgraph/checkpoint/mysql/_ainternal.py
langgraph/checkpoint/mysql/_internal.py
langgraph/checkpoint/mysql/aio.py
langgraph/checkpoint/mysql/aio_base.py
langgraph/checkpoint/mysql/asyncmy.py
langgraph/checkpoint/mysql/base.py
langgraph/checkpoint/mysql/py.typed
langgraph/checkpoint/mysql/pymysql.py
langgraph/checkpoint/mysql/shallow.py
langgraph/checkpoint/mysql/utils.py
langgraph/store/mysql/__init__.py
langgraph/store/mysql/aio.py
langgraph/store/mysql/aio_base.py
langgraph/store/mysql/asyncmy.py
langgraph/store/mysql/base.py
langgraph/store/mysql/py.typed
langgraph/store/mysql/pymysql.py
langgraph_checkpoint_mysql-2.0.17.dist-info/METADATA
langgraph_checkpoint_mysql-2.0.17.dist-info/WHEEL
langgraph_checkpoint_mysql-2.0.17.dist-info/licenses/LICENSE
langgraph_checkpoint_mysql-2.0.17.dist-info/RECORD
